burp/__init__.py
burp/burp.py
burp-1.27.dist-info/METADATA
burp-1.27.dist-info/WHEEL
burp-1.27.dist-info/top_level.txt
burp-1.27.dist-info/RECORD
