Metadata-Version: 1.1
Name: burp
Version: 1.27
Summary: Annotated burp interfaces for python/jython
Home-page: https://github.com/elnerd/burp-interfaces
Author: Erlend Leiknes
Author-email: dev@leikn.es
License: MIT
Platform: UNKNOWN
Classifier: Programming Language :: Python :: 2.7
Classifier: Programming Language :: Python :: Implementation :: Jython
Classifier: Intended Audience :: Developers
